algorithms/__init__.py
algorithms/aeti.py
algorithms/agbp.py
algorithms/common.py
algorithms/gbwp.py
algorithms/nbwp.py
cli/__init__.py
cli/cli.py
tests/__init__.py
tests/test_cli.py
utils/__init__.py
utils/exception.py
utils/helpers.py
utils/logging.py
wapor-0.2.2.dist-info/METADATA
wapor-0.2.2.dist-info/RECORD
wapor-0.2.2.dist-info/WHEEL
wapor-0.2.2.dist-info/entry_points.txt
wapor-0.2.2.dist-info/top_level.txt
