Metadata-Version: 2.1
Name: wapor
Version: 0.2.2
Summary: Wapor algorithms
Home-page: https://github.com/francbartoli/wapor
Author: Francesco Bartoli
Author-email: francesco.bartoli@geobeyond.it
License: GPLv3 license
Keywords: wapor
Platform: UNKNOWN
Classifier: Development Status :: 2 - Pre-Alpha
Classifier: Intended Audience :: Developers
Classifier: License :: OSI Approved :: MIT License
Classifier: Natural Language :: English
Classifier: Programming Language :: Python :: 2
Classifier: Programming Language :: Python :: 2.7
Classifier: Programming Language :: Python :: 3
Classifier: Programming Language :: Python :: 3.4
Classifier: Programming Language :: Python :: 3.5
Classifier: Programming Language :: Python :: 3.6
Requires-Dist: earthengine-api
Requires-Dist: daiquiri
Requires-Dist: requests-oauthlib
Requires-Dist: google-auth-oauthlib
Requires-Dist: click
Requires-Dist: dask[complete]
Requires-Dist: click-configfile
Requires-Dist: pendulum
Requires-Dist: gee-pheno
Requires-Dist: marmee
Requires-Dist: oauth2client
Requires-Dist: toolz
